lcrpm-0.1.0.dist-info/licenses/LICENSE
modeling/__init__.py
modeling/nonparametric.py
modeling/parametric.py
modeling/semiparametric.py
lcrpm-0.1.0.dist-info/METADATA
lcrpm-0.1.0.dist-info/WHEEL
lcrpm-0.1.0.dist-info/top_level.txt
lcrpm-0.1.0.dist-info/RECORD
