Metadata-Version: 2.4
Name: lcrpm
Version: 0.1.0
Summary: Lung cancer risk profiling using time-to-event modeling (LCRPM)
Author: Yusuf Brima
Author-email: Yusuf Brima <yusuf.brima@scai.fraunhofer.de>
License-Expression: MIT AND (Apache-2.0 OR BSD-2-Clause)
Classifier: Programming Language :: Python :: 3
Classifier: Operating System :: OS Independent
Requires-Python: >=3.7
License-File: LICENSE
Requires-Dist: pandas
Requires-Dist: sqlalchemy
Requires-Dist: psycopg2
Requires-Dist: python-dotenv
Requires-Dist: numpy
Dynamic: author
Dynamic: license-file
Dynamic: requires-python
